{
  "Block/": {
    "valueHash": "68934a3e9455fa72420237eb05902327",
    "isUserSet": false,
    "isActiveInStructure": true,
    "lastSeen": 1749088110679
  },
  "Description.md": {
    "valueHash": "68934a3e9455fa72420237eb05902327",
    "isUserSet": false,
    "isActiveInStructure": true,
    "lastSeen": 1749088110679
  },
  "Entity/": {
    "valueHash": "68934a3e9455fa72420237eb05902327",
    "isUserSet": false,
    "isActiveInStructure": true,
    "lastSeen": 1749088110679
  },
  "GlobalScope/": {
    "valueHash": "68934a3e9455fa72420237eb05902327",
    "isUserSet": false,
    "isActiveInStructure": true,
    "lastSeen": 1749088110679
  },
  "Item/": {
    "valueHash": "68934a3e9455fa72420237eb05902327",
    "isUserSet": false,
    "isActiveInStructure": true,
    "lastSeen": 1749088110679
  },
  "LootTable/": {
    "valueHash": "68934a3e9455fa72420237eb05902327",
    "isUserSet": false,
    "isActiveInStructure": true,
    "lastSeen": 1749088110679
  },
  "Miscellaneous/": {
    "valueHash": "68934a3e9455fa72420237eb05902327",
    "isUserSet": false,
    "isActiveInStructure": true,
    "lastSeen": 1749088110679
  },
  "Network/": {
    "valueHash": "68934a3e9455fa72420237eb05902327",
    "isUserSet": false,
    "isActiveInStructure": true,
    "lastSeen": 1749088110679
  },
  "PotionEffect/": {
    "valueHash": "68934a3e9455fa72420237eb05902327",
    "isUserSet": false,
    "isActiveInStructure": true,
    "lastSeen": 1749088110679
  },
  "Recipe/": {
    "valueHash": "68934a3e9455fa72420237eb05902327",
    "isUserSet": false,
    "isActiveInStructure": true,
    "lastSeen": 1749088110679
  },
  "Tag/": {
    "valueHash": "68934a3e9455fa72420237eb05902327",
    "isUserSet": false,
    "isActiveInStructure": true,
    "lastSeen": 1749088110679
  },
  "1.20.1/Introduction/Description.md": {
    "valueHash": "68934a3e9455fa72420237eb05902327",
    "isUserSet": true,
    "isActiveInStructure": false,
    "lastSeen": 1749088110679
  },
  "_self_": {
    "valueHash": "68934a3e9455fa72420237eb05902327",
    "isUserSet": true,
    "isActiveInStructure": false,
    "lastSeen": 1749088110679
  }
}