{
  "API.md": {
    "valueHash": "68934a3e9455fa72420237eb05902327",
    "isUserSet": true,
    "isActiveInStructure": true,
    "lastSeen": 1749087714302
  },
  "error.md": {
    "valueHash": "68934a3e9455fa72420237eb05902327",
    "isUserSet": true,
    "isActiveInStructure": true,
    "lastSeen": 1749087714302
  },
  "event_interaction.md": {
    "valueHash": "68934a3e9455fa72420237eb05902327",
    "isUserSet": true,
    "isActiveInStructure": true,
    "lastSeen": 1749087714302
  },
  "forgeEvents.md": {
    "valueHash": "68934a3e9455fa72420237eb05902327",
    "isUserSet": true,
    "isActiveInStructure": true,
    "lastSeen": 1749087714302
  },
  "loadClass.md": {
    "valueHash": "68934a3e9455fa72420237eb05902327",
    "isUserSet": true,
    "isActiveInStructure": true,
    "lastSeen": 1749087714302
  },
  "other.md": {
    "valueHash": "68934a3e9455fa72420237eb05902327",
    "isUserSet": true,
    "isActiveInStructure": true,
    "lastSeen": 1749087714302
  },
  "register.md": {
    "valueHash": "68934a3e9455fa72420237eb05902327",
    "isUserSet": true,
    "isActiveInStructure": true,
    "lastSeen": 1749087714302
  },
  "_self_": {
    "valueHash": "68934a3e9455fa72420237eb05902327",
    "isUserSet": true,
    "isActiveInStructure": false,
    "lastSeen": 1749087714302
  }
}